Metadata-Version: 1.0
Name: ai_eye
Version: 0.0.5
Summary: get the eye state from the landmarks of the face in the image
Home-page: http://www.zhaomingming.cn
Author: zhaomingming
Author-email: 13271929138@163.com
License: MIT
Platform: any
